sane_rich_logging/__init__.py
sane_rich_logging/__main__.py
sane_rich_logging/_logger.py
sane_rich_logging/py.typed
sane_rich_logging-1.0.3.dist-info/METADATA
sane_rich_logging-1.0.3.dist-info/WHEEL
sane_rich_logging-1.0.3.dist-info/licenses/LICENSE
sane_rich_logging-1.0.3.dist-info/RECORD
