Metadata-Version: 2.4
Name: sane-rich-logging
Version: 1.0.3
Summary: Add your description here
Project-URL: Homepage, https://pypi.org/project/sane-rich-logging/
Project-URL: Repository, https://github.com/jakob1379/sane-rich-logging.git
Project-URL: Issues, https://github.com/jakob1379/sane-rich-logging/issues
Project-URL: Changelog, https://github.com/jakob1379/sane-rich-logging/blob/main/CHANGELOG.md
Author-email: Jakob Guldberg Aaes <jakob1379@gmail.com>
License-File: LICENSE
Requires-Python: >=3.10
Requires-Dist: rich>=13.9.4
